monoqueue/__init__.py
monoqueue/__main__.py
monoqueue/cli.py
monoqueue/discourse.py
monoqueue/firefox.py
monoqueue/github.py
monoqueue/log.py
monoqueue/parse.py
monoqueue/time.py
monoqueue/ui.py
monoqueue-1.1.0.dist-info/METADATA
monoqueue-1.1.0.dist-info/WHEEL
monoqueue-1.1.0.dist-info/entry_points.txt
monoqueue-1.1.0.dist-info/top_level.txt
monoqueue-1.1.0.dist-info/RECORD
