Metadata-Version: 2.1
Name: monoqueue
Version: 1.1.0
Summary: Fight burnout. Stay organized.
Author-email: Curtis Rueden <ctrueden@wisc.edu>
License: The Unlicense
Project-URL: homepage, https://github.com/ctrueden/monoqueue
Project-URL: documentation, https://github.com/ctrueden/monoqueue/blob/main/README.md
Project-URL: source, https://github.com/ctrueden/monoqueue
Project-URL: download, https://pypi.org/project/monoqueue/
Project-URL: tracker, https://github.com/ctrueden/monoqueue/issues
Keywords: support,queue
Classifier: Development Status :: 5 - Production/Stable
Classifier: Intended Audience :: Developers
Classifier: Programming Language :: Python :: 3 :: Only
Classifier: Programming Language :: Python :: 3.9
Classifier: Programming Language :: Python :: 3.10
Classifier: Programming Language :: Python :: 3.11
Classifier: License :: OSI Approved :: The Unlicense (Unlicense)
Classifier: Operating System :: Microsoft :: Windows
Classifier: Operating System :: Unix
Classifier: Operating System :: MacOS
Classifier: Topic :: Software Development :: Libraries :: Python Modules
Classifier: Topic :: Utilities
Requires-Python: >=3.9
Requires-Dist: requests
Provides-Extra: dev
Requires-Dist: build ; extra == 'dev'
